oncallclient/__init__.py
oncallclient/compat.py
oncallclient-1.1.0.dist-info/METADATA
oncallclient-1.1.0.dist-info/RECORD
oncallclient-1.1.0.dist-info/WHEEL
oncallclient-1.1.0.dist-info/top_level.txt
